ledwall/__init__.py
ledwall/components/__init__.py
ledwall/components/application.py
ledwall/components/asyncsender.py
ledwall/components/color.py
ledwall/components/colorconversion.py
ledwall/components/colortable.py
ledwall/components/consolesender.py
ledwall/components/display.py
ledwall/components/hsvcolor.py
ledwall/components/listsender.py
ledwall/components/mqttsender.py
ledwall/components/multidisplay.py
ledwall/components/progmemsender.py
ledwall/components/rgbcolor.py
ledwall/components/sender.py
ledwall/components/serialsender.py
ledwall/components/sprite.py
ledwall/components/tcpsender.py
ledwall/components/udpsender.py
ledwall/components/event/__init__.py
ledwall/components/event/eventqueue.py
ledwall/components/event/framerateemitter.py
ledwall/components/event/gamepademitter.py
ledwall/components/event/keyboardemitter.py
ledwall/components/event/serialemitter.py
ledwall/games/__init__.py
ledwall/games/tetris.py
ledwall/geometry/__init__.py
ledwall/geometry/dimension.py
ledwall/geometry/line.py
ledwall/geometry/point.py
ledwall/geometry/rectangle.py
ledwall/util/__init__.py
ledwall/util/arduino.py
ledwall/util/settings.py
ledwall/util/timedelta.py
ledwall/weather/__init__.py
ledwall/weather/weather.py
ledwall/widgets/__init__.py
ledwall/widgets/clocks.py
ledwall-1.0.12.dist-info/LICENSE
ledwall-1.0.12.dist-info/METADATA
ledwall-1.0.12.dist-info/WHEEL
ledwall-1.0.12.dist-info/top_level.txt
ledwall-1.0.12.dist-info/RECORD
