Metadata-Version: 2.1
Name: ledwall
Version: 1.0.12
Summary: A simple but powerful library to control WS2812b LED panel.
Home-page: https://github.com/FirstKlaas/LEDWall/tree/master/python
Author: Klaas Nebuhr (FirstKlaas)
Author-email: klaas@nebuhr.de
License: UNKNOWN
Platform: UNKNOWN
Classifier: Programming Language :: Python :: 3 :: Only
Classifier: License :: OSI Approved :: MIT License
Classifier: Operating System :: OS Independent
Requires-Dist: inputs
Requires-Dist: paho-mqtt
Requires-Dist: pyserial
